rousquille_tools/__init__.py
rousquille_tools/decorators.py
rousquille_tools/shell.py
rousquille_tools-0.1.2.dist-info/WHEEL
rousquille_tools-0.1.2.dist-info/METADATA
rousquille_tools-0.1.2.dist-info/RECORD
