Metadata-Version: 2.1
Name: rousquille-tools
Version: 0.1.2
Summary: My personal toolbox
Home-page: https://github.com/rousquille/rousquille-tools
License: MIT
Author: Fabien ROSSA
Requires-Python: >=3.9,<4.0
Classifier: License :: OSI Approved :: MIT License
Classifier: Programming Language :: Python :: 3
Classifier: Programming Language :: Python :: 3.9
Classifier: Programming Language :: Python :: 3.10
Classifier: Programming Language :: Python :: 3.11
Project-URL: Repository, https://github.com/rousquille/rousquille-tools
